llama_index/multi_modal_llms/openai/__init__.py
llama_index/multi_modal_llms/openai/base.py
llama_index_multi_modal_llms_openai-0.6.1.dist-info/METADATA
llama_index_multi_modal_llms_openai-0.6.1.dist-info/WHEEL
llama_index_multi_modal_llms_openai-0.6.1.dist-info/licenses/LICENSE
llama_index_multi_modal_llms_openai-0.6.1.dist-info/RECORD
